[
  {
    "caption": "(4) 보고기간종료일 현재 기간별 보험계약마진 상각금액은 다음과 같습니다.",
    "line_no": 11971,
    "score": 6,
    "form_type": "A",
    "reasons": [
      "caption: CSM + (상각/예상/인식/향후)",
      "header: 15 year-bucket cells",
      "header: has 합계/계 column"
    ],
    "header": [
      [
        "구 분",
        "1년",
        "2년",
        "3년",
        "4년",
        "5년",
        "6년",
        "7년",
        "8년",
        "9년",
        "10년",
        "11년~15년",
        "16년~20년",
        "21년~25년",
        "26년~30년",
        "30년 이후",
        "총계"
      ]
    ],
    "rows": [
      [
        "Non-Par",
        "무배당상해",
        "33,976",
        "29,692",
        "23,578",
        "20,073",
        "18,307",
        "17,534",
        "16,859",
        "16,383",
        "16,155",
        "16,024",
        "78,457",
        "74,920",
        "74,145",
        "71,391",
        "342,863",
        "850,357"
      ],
      [
        "무배당질병",
        "12,505",
        "12,442",
        "11,749",
        "10,168",
        "9,006",
        "7,547",
        "6,697",
        "6,153",
        "5,728",
        "5,427",
        "24,027",
        "19,336",
        "14,899",
        "10,529",
        "15,559",
        "171,772"
      ],
      [
        "무배당재물",
        "5,391",
        "6,013",
        "5,887",
        "5,368",
        "4,719",
        "4,416",
        "3,915",
        "3,085",
        "2,117",
        "1,178",
        "2,298",
        "-",
        "-",
        "-",
        "-",
        "44,387"
      ],
      [
        "무배당연금/저축",
        "381",
        "383",
        "341",
        "343",
        "357",
        "378",
        "362",
        "-",
        "-",
        "-",
        "-",
        "-",
        "-",
        "-",
        "-",
        "2,545"
      ],
      [
        "무배당기타",
        "52",
        "45",
        "39",
        "34",
        "29",
        "26",
        "23",
        "18",
        "11",
        "6",
        "11",
        "5",
        "-",
        "-",
        "-",
        "299"
      ],
      [
        "소 계",
        "52,305",
        "48,575",
        "41,594",
        "35,986",
        "32,418",
        "29,901",
        "27,856",
        "25,639",
        "24,011",
        "22,635",
        "104,793",
        "94,261",
        "89,044",
        "81,920",
        "358,422",
        "1,069,360"
      ],
      [
        "Indirect-Par",
        "무배당상해",
        "7,821",
        "8,996",
        "10,048",
        "10,888",
        "9,597",
        "9,025",
        "8,555",
        "7,767",
        "6,951",
        "6,224",
        "28,416",
        "17,797",
        "8,141",
        "6,842",
        "25,988",
        "173,056"
      ],
      [
        "무배당질병",
        "5,953",
        "6,289",
        "6,583",
        "6,211",
        "5,610",
        "5,577",
        "5,640",
        "5,781",
        "5,146",
        "4,654",
        "22,381",
        "15,951",
        "12,243",
        "8,101",
        "15,762",
        "131,882"
      ],
      [
        "무배당재물",
        "21,003",
        "22,539",
        "23,727",
        "21,523",
        "16,872",
        "13,709",
        "11,730",
        "9,457",
        "6,965",
        "4,027",
        "6,224",
        "49",
        "8",
        "-",
        "-",
        "157,833"
      ],
      [
        "무배당연금/저축",
        "4,590",
        "3,689",
        "2,055",
        "912",
        "419",
        "190",
        "89",
        "39",
        "14",
        "4",
        "3",
        "-",
        "-",
        "-",
        "-",
        "12,004"
      ],
      [
        "무배당기타",
        "5,426",
        "5,667",
        "5,762",
        "5,566",
        "5,035",
        "4,417",
        "3,770",
        "2,725",
        "2,000",
        "1,503",
        "5,152",
        "2,250",
        "449",
        "328",
        "732",
        "50,782"
      ],
      [
        "소 계",
        "44,793",
        "47,180",
        "48,175",
        "45,100",
        "37,533",
        "32,918",
        "29,784",
        "25,769",
        "21,076",
        "16,412",
        "62,176",
        "36,047",
        "20,841",
        "15,271",
        "42,482",
        "525,557"
      ],
      [
        "합 계",
        "97,098",
        "95,755",
        "89,769",
        "81,086",
        "69,951",
        "62,819",
        "57,640",
        "51,408",
        "45,087",
        "39,047",
        "166,969",
        "130,308",
        "109,885",
        "97,191",
        "400,904",
        "1,594,917"
      ]
    ],
    "footnotes": [],
    "_source_xml": "20260331004099.xml"
  },
  {
    "caption": "(4) 보고기간종료일 현재 기간별 보험계약마진 상각금액은 다음과 같습니다.",
    "line_no": 12316,
    "score": 6,
    "form_type": "A",
    "reasons": [
      "caption: CSM + (상각/예상/인식/향후)",
      "header: 15 year-bucket cells",
      "header: has 합계/계 column"
    ],
    "header": [
      [
        "구 분",
        "1년",
        "2년",
        "3년",
        "4년",
        "5년",
        "6년",
        "7년",
        "8년",
        "9년",
        "10년",
        "11년~15년",
        "16년~20년",
        "21년~25년",
        "26년~30년",
        "30년 이후",
        "총계"
      ]
    ],
    "rows": [
      [
        "Non-Par",
        "무배당상해",
        "18,661",
        "16,755",
        "15,314",
        "14,070",
        "13,269",
        "12,868",
        "12,603",
        "12,413",
        "12,286",
        "12,241",
        "100,492",
        "100,492",
        "66,481",
        "66,481",
        "165,162",
        "639,588"
      ],
      [
        "무배당질병",
        "17,074",
        "17,106",
        "17,020",
        "16,253",
        "14,615",
        "13,588",
        "12,071",
        "10,924",
        "10,218",
        "9,656",
        "47,123",
        "47,123",
        "22,515",
        "22,515",
        "22,667",
        "300,468"
      ],
      [
        "무배당재물",
        "8,541",
        "7,235",
        "5,466",
        "3,885",
        "2,647",
        "2,082",
        "1,867",
        "1,323",
        "767",
        "309",
        "516",
        "41",
        "-",
        "-",
        "-",
        "34,679"
      ],
      [
        "무배당연금/저축",
        "442",
        "387",
        "371",
        "339",
        "346",
        "358",
        "374",
        "323",
        "-",
        "-",
        "-",
        "-",
        "-",
        "-",
        "-",
        "2,940"
      ],
      [
        "무배당기타",
        "37",
        "32",
        "27",
        "24",
        "21",
        "18",
        "16",
        "15",
        "11",
        "4",
        "6",
        "6",
        "-",
        "-",
        "-",
        "217"
      ],
      [
        "소 계",
        "44,755",
        "41,515",
        "38,198",
        "34,571",
        "30,898",
        "28,914",
        "26,931",
        "24,998",
        "23,282",
        "22,210",
        "148,137",
        "147,662",
        "88,996",
        "88,996",
        "187,829",
        "977,892"
      ],
      [
        "Indirect-Par",
        "무배당상해",
        "12,662",
        "11,729",
        "10,966",
        "10,269",
        "9,458",
        "8,372",
        "7,502",
        "6,626",
        "5,968",
        "5,380",
        "20,986",
        "20,986",
        "8,472",
        "8,472",
        "13,766",
        "161,614"
      ],
      [
        "무배당질병",
        "8,832",
        "8,040",
        "7,390",
        "6,782",
        "6,244",
        "5,757",
        "5,370",
        "5,041",
        "4,752",
        "4,403",
        "18,004",
        "18,004",
        "6,431",
        "6,431",
        "4,764",
        "116,245"
      ],
      [
        "무배당재물",
        "42,553",
        "34,838",
        "29,369",
        "24,808",
        "18,175",
        "12,391",
        "8,603",
        "6,037",
        "3,755",
        "1,780",
        "2,222",
        "241",
        "36",
        "-",
        "-",
        "184,808"
      ],
      [
        "무배당연금/저축",
        "4,039",
        "3,540",
        "2,823",
        "1,564",
        "817",
        "361",
        "131",
        "65",
        "30",
        "9",
        "7",
        "-",
        "-",
        "-",
        "-",
        "13,386"
      ],
      [
        "무배당기타",
        "10,487",
        "8,823",
        "7,541",
        "6,433",
        "5,327",
        "4,314",
        "3,422",
        "2,772",
        "1,957",
        "1,352",
        "3,016",
        "3,016",
        "270",
        "270",
        "281",
        "59,281"
      ],
      [
        "소 계",
        "78,573",
        "66,970",
        "58,089",
        "49,856",
        "40,021",
        "31,195",
        "25,028",
        "20,541",
        "16,462",
        "12,924",
        "44,235",
        "42,247",
        "15,209",
        "15,173",
        "18,811",
        "535,334"
      ],
      [
        "합 계",
        "123,328",
        "108,485",
        "96,287",
        "84,427",
        "70,919",
        "60,109",
        "51,959",
        "45,539",
        "39,744",
        "35,134",
        "192,372",
        "189,909",
        "104,205",
        "104,169",
        "206,640",
        "1,513,226"
      ]
    ],
    "footnotes": [],
    "_source_xml": "20260331004099.xml"
  },
  {
    "caption": "(14) 당기말 및 전기말 현재 보험계약마진의 기간별 손익 인식 예정액은 다음과 같습니다.",
    "line_no": 21310,
    "score": 6,
    "form_type": "A",
    "reasons": [
      "caption: CSM + (상각/예상/인식/향후)",
      "header: 5 year-bucket cells",
      "header: has 합계/계 column"
    ],
    "header": [
      [
        "구분",
        "1년이하",
        "1년초과 3년이하",
        "3년초과 5년이하",
        "5년초과 10년이하",
        "10년초과",
        "합계"
      ]
    ],
    "rows": [
      [
        "보험계약",
        "97,098",
        "185,524",
        "151,037",
        "256,001",
        "905,257",
        "1,594,917"
      ],
      [
        "재보험계약",
        "(24,630)",
        "(41,807)",
        "(32,469)",
        "(47,532)",
        "(43,800)",
        "(190,238)"
      ]
    ],
    "footnotes": [],
    "_source_xml": "20260331004099.xml"
  },
  {
    "caption": "(14) 당기말 및 전기말 현재 보험계약마진의 기간별 손익 인식 예정액은 다음과 같습니다.",
    "line_no": 21376,
    "score": 6,
    "form_type": "A",
    "reasons": [
      "caption: CSM + (상각/예상/인식/향후)",
      "header: 5 year-bucket cells",
      "header: has 합계/계 column"
    ],
    "header": [
      [
        "구분",
        "1년이하",
        "1년초과 3년이하",
        "3년초과 5년이하",
        "5년초과 10년이하",
        "10년초과",
        "합계"
      ]
    ],
    "rows": [
      [
        "보험계약",
        "123,328",
        "204,772",
        "155,346",
        "232,485",
        "797,295",
        "1,513,226"
      ],
      [
        "재보험계약",
        "(7,999)",
        "(15,079)",
        "(12,709)",
        "(16,002)",
        "(2,413)",
        "(54,202)"
      ]
    ],
    "footnotes": [],
    "_source_xml": "20260331004099.xml"
  },
  {
    "caption": "(4) 보고기간종료일 현재 기간별 보험계약마진 상각금액은 다음과 같습니다.",
    "line_no": 6895,
    "score": 6,
    "form_type": "A",
    "reasons": [
      "caption: CSM + (상각/예상/인식/향후)",
      "header: 15 year-bucket cells",
      "header: has 합계/계 column"
    ],
    "header": [
      [
        "구 분",
        "1년",
        "2년",
        "3년",
        "4년",
        "5년",
        "6년",
        "7년",
        "8년",
        "9년",
        "10년",
        "11년~15년",
        "16년~20년",
        "21년~25년",
        "26년~30년",
        "30년 이후",
        "총계"
      ]
    ],
    "rows": [
      [
        "Non-Par",
        "무배당상해",
        "33,976",
        "29,692",
        "23,578",
        "20,073",
        "18,307",
        "17,534",
        "16,859",
        "16,383",
        "16,155",
        "16,024",
        "78,457",
        "74,920",
        "74,145",
        "71,391",
        "342,863",
        "850,357"
      ],
      [
        "무배당질병",
        "12,505",
        "12,442",
        "11,749",
        "10,168",
        "9,006",
        "7,547",
        "6,697",
        "6,153",
        "5,728",
        "5,427",
        "24,027",
        "19,336",
        "14,899",
        "10,529",
        "15,559",
        "171,772"
      ],
      [
        "무배당재물",
        "5,391",
        "6,013",
        "5,887",
        "5,368",
        "4,719",
        "4,416",
        "3,915",
        "3,085",
        "2,117",
        "1,178",
        "2,298",
        "-",
        "-",
        "-",
        "-",
        "44,387"
      ],
      [
        "무배당연금/저축",
        "381",
        "383",
        "341",
        "343",
        "357",
        "378",
        "362",
        "-",
        "-",
        "-",
        "-",
        "-",
        "-",
        "-",
        "-",
        "2,545"
      ],
      [
        "무배당기타",
        "52",
        "45",
        "39",
        "34",
        "29",
        "26",
        "23",
        "18",
        "11",
        "6",
        "11",
        "5",
        "-",
        "-",
        "-",
        "299"
      ],
      [
        "소 계",
        "52,305",
        "48,575",
        "41,594",
        "35,986",
        "32,418",
        "29,901",
        "27,856",
        "25,639",
        "24,011",
        "22,635",
        "104,793",
        "94,261",
        "89,044",
        "81,920",
        "358,422",
        "1,069,360"
      ],
      [
        "Indirect-Par",
        "무배당상해",
        "7,821",
        "8,996",
        "10,048",
        "10,888",
        "9,597",
        "9,025",
        "8,555",
        "7,767",
        "6,951",
        "6,224",
        "28,416",
        "17,797",
        "8,141",
        "6,842",
        "25,988",
        "173,056"
      ],
      [
        "무배당질병",
        "5,953",
        "6,289",
        "6,583",
        "6,211",
        "5,610",
        "5,577",
        "5,640",
        "5,781",
        "5,146",
        "4,654",
        "22,381",
        "15,951",
        "12,243",
        "8,101",
        "15,762",
        "131,882"
      ],
      [
        "무배당재물",
        "21,003",
        "22,539",
        "23,727",
        "21,523",
        "16,872",
        "13,709",
        "11,730",
        "9,457",
        "6,965",
        "4,027",
        "6,224",
        "49",
        "8",
        "-",
        "-",
        "157,833"
      ],
      [
        "무배당연금/저축",
        "4,590",
        "3,689",
        "2,055",
        "912",
        "419",
        "190",
        "89",
        "39",
        "14",
        "4",
        "3",
        "-",
        "-",
        "-",
        "-",
        "12,004"
      ],
      [
        "무배당기타",
        "5,426",
        "5,667",
        "5,762",
        "5,566",
        "5,035",
        "4,417",
        "3,770",
        "2,725",
        "2,000",
        "1,503",
        "5,152",
        "2,250",
        "449",
        "328",
        "732",
        "50,782"
      ],
      [
        "소 계",
        "44,793",
        "47,180",
        "48,175",
        "45,100",
        "37,533",
        "32,918",
        "29,784",
        "25,769",
        "21,076",
        "16,412",
        "62,176",
        "36,047",
        "20,841",
        "15,271",
        "42,482",
        "525,557"
      ],
      [
        "합 계",
        "97,098",
        "95,755",
        "89,769",
        "81,086",
        "69,951",
        "62,819",
        "57,640",
        "51,408",
        "45,087",
        "39,047",
        "166,969",
        "130,308",
        "109,885",
        "97,191",
        "400,904",
        "1,594,917"
      ]
    ],
    "footnotes": [],
    "_source_xml": "20260331004099_00760.xml"
  },
  {
    "caption": "(4) 보고기간종료일 현재 기간별 보험계약마진 상각금액은 다음과 같습니다.",
    "line_no": 7240,
    "score": 6,
    "form_type": "A",
    "reasons": [
      "caption: CSM + (상각/예상/인식/향후)",
      "header: 15 year-bucket cells",
      "header: has 합계/계 column"
    ],
    "header": [
      [
        "구 분",
        "1년",
        "2년",
        "3년",
        "4년",
        "5년",
        "6년",
        "7년",
        "8년",
        "9년",
        "10년",
        "11년~15년",
        "16년~20년",
        "21년~25년",
        "26년~30년",
        "30년 이후",
        "총계"
      ]
    ],
    "rows": [
      [
        "Non-Par",
        "무배당상해",
        "18,661",
        "16,755",
        "15,314",
        "14,070",
        "13,269",
        "12,868",
        "12,603",
        "12,413",
        "12,286",
        "12,241",
        "100,492",
        "100,492",
        "66,481",
        "66,481",
        "165,162",
        "639,588"
      ],
      [
        "무배당질병",
        "17,074",
        "17,106",
        "17,020",
        "16,253",
        "14,615",
        "13,588",
        "12,071",
        "10,924",
        "10,218",
        "9,656",
        "47,123",
        "47,123",
        "22,515",
        "22,515",
        "22,667",
        "300,468"
      ],
      [
        "무배당재물",
        "8,541",
        "7,235",
        "5,466",
        "3,885",
        "2,647",
        "2,082",
        "1,867",
        "1,323",
        "767",
        "309",
        "516",
        "41",
        "-",
        "-",
        "-",
        "34,679"
      ],
      [
        "무배당연금/저축",
        "442",
        "387",
        "371",
        "339",
        "346",
        "358",
        "374",
        "323",
        "-",
        "-",
        "-",
        "-",
        "-",
        "-",
        "-",
        "2,940"
      ],
      [
        "무배당기타",
        "37",
        "32",
        "27",
        "24",
        "21",
        "18",
        "16",
        "15",
        "11",
        "4",
        "6",
        "6",
        "-",
        "-",
        "-",
        "217"
      ],
      [
        "소 계",
        "44,755",
        "41,515",
        "38,198",
        "34,571",
        "30,898",
        "28,914",
        "26,931",
        "24,998",
        "23,282",
        "22,210",
        "148,137",
        "147,662",
        "88,996",
        "88,996",
        "187,829",
        "977,892"
      ],
      [
        "Indirect-Par",
        "무배당상해",
        "12,662",
        "11,729",
        "10,966",
        "10,269",
        "9,458",
        "8,372",
        "7,502",
        "6,626",
        "5,968",
        "5,380",
        "20,986",
        "20,986",
        "8,472",
        "8,472",
        "13,766",
        "161,614"
      ],
      [
        "무배당질병",
        "8,832",
        "8,040",
        "7,390",
        "6,782",
        "6,244",
        "5,757",
        "5,370",
        "5,041",
        "4,752",
        "4,403",
        "18,004",
        "18,004",
        "6,431",
        "6,431",
        "4,764",
        "116,245"
      ],
      [
        "무배당재물",
        "42,553",
        "34,838",
        "29,369",
        "24,808",
        "18,175",
        "12,391",
        "8,603",
        "6,037",
        "3,755",
        "1,780",
        "2,222",
        "241",
        "36",
        "-",
        "-",
        "184,808"
      ],
      [
        "무배당연금/저축",
        "4,039",
        "3,540",
        "2,823",
        "1,564",
        "817",
        "361",
        "131",
        "65",
        "30",
        "9",
        "7",
        "-",
        "-",
        "-",
        "-",
        "13,386"
      ],
      [
        "무배당기타",
        "10,487",
        "8,823",
        "7,541",
        "6,433",
        "5,327",
        "4,314",
        "3,422",
        "2,772",
        "1,957",
        "1,352",
        "3,016",
        "3,016",
        "270",
        "270",
        "281",
        "59,281"
      ],
      [
        "소 계",
        "78,573",
        "66,970",
        "58,089",
        "49,856",
        "40,021",
        "31,195",
        "25,028",
        "20,541",
        "16,462",
        "12,924",
        "44,235",
        "42,247",
        "15,209",
        "15,173",
        "18,811",
        "535,334"
      ],
      [
        "합 계",
        "123,328",
        "108,485",
        "96,287",
        "84,427",
        "70,919",
        "60,109",
        "51,959",
        "45,539",
        "39,744",
        "35,134",
        "192,372",
        "189,909",
        "104,205",
        "104,169",
        "206,640",
        "1,513,226"
      ]
    ],
    "footnotes": [],
    "_source_xml": "20260331004099_00760.xml"
  },
  {
    "caption": "(14) 당기말 및 전기말 현재 보험계약마진의 기간별 손익 인식 예정액은 다음과 같습니다.",
    "line_no": 16234,
    "score": 6,
    "form_type": "A",
    "reasons": [
      "caption: CSM + (상각/예상/인식/향후)",
      "header: 5 year-bucket cells",
      "header: has 합계/계 column"
    ],
    "header": [
      [
        "구분",
        "1년이하",
        "1년초과 3년이하",
        "3년초과 5년이하",
        "5년초과 10년이하",
        "10년초과",
        "합계"
      ]
    ],
    "rows": [
      [
        "보험계약",
        "97,098",
        "185,524",
        "151,037",
        "256,001",
        "905,257",
        "1,594,917"
      ],
      [
        "재보험계약",
        "(24,630)",
        "(41,807)",
        "(32,469)",
        "(47,532)",
        "(43,800)",
        "(190,238)"
      ]
    ],
    "footnotes": [],
    "_source_xml": "20260331004099_00760.xml"
  },
  {
    "caption": "(14) 당기말 및 전기말 현재 보험계약마진의 기간별 손익 인식 예정액은 다음과 같습니다.",
    "line_no": 16300,
    "score": 6,
    "form_type": "A",
    "reasons": [
      "caption: CSM + (상각/예상/인식/향후)",
      "header: 5 year-bucket cells",
      "header: has 합계/계 column"
    ],
    "header": [
      [
        "구분",
        "1년이하",
        "1년초과 3년이하",
        "3년초과 5년이하",
        "5년초과 10년이하",
        "10년초과",
        "합계"
      ]
    ],
    "rows": [
      [
        "보험계약",
        "123,328",
        "204,772",
        "155,346",
        "232,485",
        "797,295",
        "1,513,226"
      ],
      [
        "재보험계약",
        "(7,999)",
        "(15,079)",
        "(12,709)",
        "(16,002)",
        "(2,413)",
        "(54,202)"
      ]
    ],
    "footnotes": [],
    "_source_xml": "20260331004099_00760.xml"
  }
]