[
  {
    "caption": "당기와 전기 중 전환시점 적용 보험계약마진의 변동내역, 보험수익 및 재보험서비스비용은 다음과 같습니다.",
    "block_type": "mixed",
    "slice_label": "long_term",
    "slice_policy": "long_term",
    "mvp_candidate": true,
    "line_no": 35752,
    "score": 11,
    "reasons": [
      "caption: P&L keywords x2",
      "header: measurement columns x3",
      "rows: strong P&L stubs x3",
      "slice: long_term label present"
    ],
    "header": [
      [
        "구분",
        "수정소급법 적용 계약집합",
        "공정가치법 적용 계약집합",
        "그 외 계약집합",
        "합계"
      ]
    ],
    "rows": [
      [
        "보험계약",
        "",
        "",
        "",
        ""
      ],
      [
        "보험계약마진",
        "",
        "",
        "",
        ""
      ],
      [
        "전기말 보험계약마진",
        "4,042,062,762",
        "2,076,570,743",
        "3,023,637,636",
        "9,142,271,141"
      ],
      [
        "미래서비스와 관련된 변동",
        "(1,247,735,021)",
        "231,489,543",
        "809,101,521",
        "(207,143,957)"
      ],
      [
        "- 보험계약마진을 조정하는 추정치의 변동분",
        "(1,247,735,021)",
        "231,489,543",
        "(1,018,777,832)",
        "(2,035,023,310)"
      ],
      [
        "- 해당 기간에 처음 인식한 계약의 효과",
        "-",
        "-",
        "1,827,879,353",
        "1,827,879,353"
      ],
      [
        "당기서비스와 관련된 변동",
        "(333,525,682)",
        "(171,269,650)",
        "(446,306,428)",
        "(951,101,760)"
      ],
      [
        "- 서비스의 이전을 반영하기 위해 당기손익으로 인식한 보험계약마진 금액",
        "(333,525,682)",
        "(171,269,650)",
        "(446,306,428)",
        "(951,101,760)"
      ],
      [
        "보험금융손익",
        "101,719,750",
        "46,962,204",
        "172,779,885",
        "321,461,839"
      ],
      [
        "당기말 보험계약마진",
        "2,562,521,809",
        "2,183,752,840",
        "3,559,212,614",
        "8,305,487,263"
      ],
      [
        "당기 보험수익",
        "2,444,403,901",
        "2,890,876,548",
        "8,378,181,263",
        "13,713,461,712"
      ],
      [
        "장기",
        "2,344,840,554",
        "2,890,876,548",
        "2,245,677,057",
        "7,481,394,159"
      ],
      [
        "자동차",
        "12,517,690",
        "-",
        "4,166,160,610",
        "4,178,678,300"
      ],
      [
        "일반",
        "87,045,657",
        "-",
        "1,966,343,596",
        "2,053,389,253"
      ],
      [
        "출재보험계약",
        "",
        "",
        "",
        ""
      ],
      [
        "보험계약마진",
        "",
        "",
        "",
        ""
      ],
      [
        "전기말 보험계약마진",
        "30,824,158",
        "13,493,019",
        "19,400,672",
        "63,717,849"
      ],
      [
        "미래서비스와 관련된 변동",
        "2,939,785",
        "(2,141,157)",
        "9,319,641",
        "10,118,269"
      ],
      [
        "- 보험계약마진을 조정하는 추정치의 변동분",
        "2,939,785",
        "(2,141,157)",
        "2,393,363",
        "3,191,991"
      ],
      [
        "- 해당 기간에 처음 인식한 계약의 효과",
        "-",
        "-",
        "6,926,278",
        "6,926,278"
      ],
      [
        "당기서비스와 관련된 변동",
        "(3,661,011)",
        "(5,862,277)",
        "(8,744,016)",
        "(18,267,304)"
      ],
      [
        "- 서비스의 이전을 반영하기 위해 당기손익으로 인식한 보험계약마진 금액",
        "(3,661,011)",
        "(5,862,277)",
        "(8,744,016)",
        "(18,267,304)"
      ],
      [
        "보험금융손익",
        "905,296",
        "316,312",
        "1,024,131",
        "2,245,739"
      ],
      [
        "당기말 보험계약마진",
        "31,008,228",
        "5,805,897",
        "21,000,428",
        "57,814,553"
      ],
      [
        "당기 재보험서비스비용",
        "39,393,294",
        "18,059,867",
        "959,444,323",
        "1,016,897,484"
      ],
      [
        "장기",
        "3,789,203",
        "18,059,867",
        "19,580,001",
        "41,429,071"
      ],
      [
        "자동차",
        "-",
        "-",
        "7,127,957",
        "7,127,957"
      ],
      [
        "일반",
        "35,604,091",
        "-",
        "932,736,365",
        "968,340,456"
      ]
    ],
    "footnotes": [],
    "_source_xml": "20250313001346.xml"
  },
  {
    "caption": "당기와 전기 중 전환시점 적용 보험계약마진의 변동내역, 보험수익 및 재보험서비스비용은 다음과 같습니다.",
    "block_type": "mixed",
    "slice_label": "long_term",
    "slice_policy": "long_term",
    "mvp_candidate": true,
    "line_no": 36017,
    "score": 11,
    "reasons": [
      "caption: P&L keywords x2",
      "header: measurement columns x3",
      "rows: strong P&L stubs x3",
      "slice: long_term label present"
    ],
    "header": [
      [
        "구분",
        "수정소급법 적용 계약집합",
        "공정가치법 적용 계약집합",
        "그 외 계약집합",
        "합계"
      ]
    ],
    "rows": [
      [
        "보험계약",
        "",
        "",
        "",
        ""
      ],
      [
        "보험계약마진",
        "",
        "",
        "",
        ""
      ],
      [
        "전전기말 보험계약마진",
        "4,773,487,276",
        "1,843,262,769",
        "1,734,787,218",
        "8,351,537,263"
      ],
      [
        "미래서비스와 관련된 변동",
        "(434,047,147)",
        "347,884,080",
        "1,493,809,496",
        "1,407,646,429"
      ],
      [
        "- 보험계약마진을 조정하는 추정치의 변동분",
        "(434,047,147)",
        "347,884,080",
        "(185,427,389)",
        "(271,590,456)"
      ],
      [
        "- 해당 기간에 처음 인식한 계약의 효과",
        "-",
        "-",
        "1,679,236,885",
        "1,679,236,885"
      ],
      [
        "당기서비스와 관련된 변동",
        "(406,585,044)",
        "(160,766,964)",
        "(313,192,835)",
        "(880,544,843)"
      ],
      [
        "- 서비스의 이전을 반영하기 위해 당기손익으로 인식한 보험계약마진 금액",
        "(406,585,044)",
        "(160,766,964)",
        "(313,192,835)",
        "(880,544,843)"
      ],
      [
        "보험금융손익",
        "109,207,676",
        "46,190,858",
        "108,233,756",
        "263,632,290"
      ],
      [
        "전기말 보험계약마진",
        "4,042,062,761",
        "2,076,570,743",
        "3,023,637,635",
        "9,142,271,139"
      ],
      [
        "전기 보험수익",
        "2,733,993,435",
        "3,033,893,242",
        "7,356,351,623",
        "13,124,238,300"
      ],
      [
        "장기",
        "2,521,873,317",
        "3,033,893,242",
        "1,369,542,114",
        "6,925,308,673"
      ],
      [
        "자동차",
        "22,542,237",
        "-",
        "4,216,631,959",
        "4,239,174,196"
      ],
      [
        "일반",
        "189,577,881",
        "-",
        "1,770,177,550",
        "1,959,755,431"
      ],
      [
        "출재보험계약",
        "",
        "",
        "",
        ""
      ],
      [
        "보험계약마진",
        "",
        "",
        "",
        ""
      ],
      [
        "전전기말 보험계약마진",
        "28,637,189",
        "3,071,373",
        "388,847",
        "32,097,409"
      ],
      [
        "미래서비스와 관련된 변동",
        "4,647,992",
        "11,144,152",
        "22,346,294",
        "38,138,438"
      ],
      [
        "- 보험계약마진을 조정하는 추정치의 변동분",
        "4,647,992",
        "11,144,152",
        "22,532,905",
        "38,325,049"
      ],
      [
        "- 해당 기간에 처음 인식한 계약의 효과",
        "-",
        "-",
        "(186,611)",
        "(186,611)"
      ],
      [
        "당기서비스와 관련된 변동",
        "(3,368,533)",
        "(805,034)",
        "(3,515,595)",
        "(7,689,162)"
      ],
      [
        "- 서비스의 이전을 반영하기 위해 당기손익으로 인식한 보험계약마진 금액",
        "(3,368,533)",
        "(805,034)",
        "(3,515,595)",
        "(7,689,162)"
      ],
      [
        "보험금융손익",
        "907,510",
        "82,528",
        "181,126",
        "1,171,164"
      ],
      [
        "전기말 보험계약마진",
        "30,824,158",
        "13,493,019",
        "19,400,672",
        "63,717,849"
      ],
      [
        "전기 재보험서비스비용",
        "93,071,169",
        "22,320,521",
        "876,709,038",
        "992,100,728"
      ],
      [
        "장기",
        "4,024,688",
        "22,320,521",
        "4,173,151",
        "30,518,360"
      ],
      [
        "자동차",
        "-",
        "-",
        "5,528,107",
        "5,528,107"
      ],
      [
        "일반",
        "89,046,481",
        "-",
        "867,007,780",
        "956,054,261"
      ]
    ],
    "footnotes": [],
    "_source_xml": "20250313001346.xml"
  },
  {
    "caption": "당기와 전기 중 전환시점 적용 보험계약마진의 변동내역, 보험수익 및 재보험서비스비용은 다음과 같습니다.",
    "block_type": "mixed",
    "slice_label": "long_term",
    "slice_policy": "long_term",
    "mvp_candidate": true,
    "line_no": 65535,
    "score": 11,
    "reasons": [
      "caption: P&L keywords x2",
      "header: measurement columns x3",
      "rows: strong P&L stubs x3",
      "slice: long_term label present"
    ],
    "header": [
      [
        "구분",
        "수정소급법 적용 계약집합",
        "공정가치법 적용 계약집합",
        "그 외 계약집합",
        "합계"
      ]
    ],
    "rows": [
      [
        "보험계약",
        "",
        "",
        "",
        ""
      ],
      [
        "보험계약마진",
        "",
        "",
        "",
        ""
      ],
      [
        "전기말 보험계약마진",
        "4,042,062,762",
        "2,076,570,743",
        "3,023,637,636",
        "9,142,271,141"
      ],
      [
        "미래서비스와 관련된 변동",
        "(1,247,735,021)",
        "231,489,543",
        "809,101,521",
        "(207,143,957)"
      ],
      [
        "- 보험계약마진을 조정하는 추정치의 변동분",
        "(1,247,735,021)",
        "231,489,543",
        "(1,018,777,832)",
        "(2,035,023,310)"
      ],
      [
        "- 해당 기간에 처음 인식한 계약의 효과",
        "-",
        "-",
        "1,827,879,353",
        "1,827,879,353"
      ],
      [
        "당기서비스와 관련된 변동",
        "(333,525,682)",
        "(171,269,650)",
        "(446,306,428)",
        "(951,101,760)"
      ],
      [
        "- 서비스의 이전을 반영하기 위해 당기손익으로 인식한 보험계약마진 금액",
        "(333,525,682)",
        "(171,269,650)",
        "(446,306,428)",
        "(951,101,760)"
      ],
      [
        "보험금융손익",
        "101,719,750",
        "46,962,204",
        "172,779,885",
        "321,461,839"
      ],
      [
        "당기말 보험계약마진",
        "2,562,521,809",
        "2,183,752,840",
        "3,559,212,614",
        "8,305,487,263"
      ],
      [
        "당기 보험수익",
        "2,444,403,901",
        "2,890,876,548",
        "8,379,729,625",
        "13,715,010,074"
      ],
      [
        "장기",
        "2,344,840,554",
        "2,890,876,548",
        "2,245,677,057",
        "7,481,394,159"
      ],
      [
        "자동차",
        "12,517,690",
        "-",
        "4,166,160,610",
        "4,178,678,300"
      ],
      [
        "일반",
        "87,045,657",
        "-",
        "1,967,891,958",
        "2,054,937,615"
      ],
      [
        "출재보험계약",
        "",
        "",
        "",
        ""
      ],
      [
        "보험계약마진",
        "",
        "",
        "",
        ""
      ],
      [
        "전기말 보험계약마진",
        "30,824,158",
        "13,493,019",
        "19,400,672",
        "63,717,849"
      ],
      [
        "미래서비스와 관련된 변동",
        "2,939,785",
        "(2,141,157)",
        "9,319,641",
        "10,118,269"
      ],
      [
        "- 보험계약마진을 조정하는 추정치의 변동분",
        "2,939,785",
        "(2,141,157)",
        "2,393,363",
        "3,191,991"
      ],
      [
        "- 해당 기간에 처음 인식한 계약의 효과",
        "-",
        "-",
        "6,926,278",
        "6,926,278"
      ],
      [
        "당기서비스와 관련된 변동",
        "(3,661,011)",
        "(5,862,277)",
        "(8,744,016)",
        "(18,267,304)"
      ],
      [
        "- 서비스의 이전을 반영하기 위해 당기손익으로 인식한 보험계약마진 금액",
        "(3,661,011)",
        "(5,862,277)",
        "(8,744,016)",
        "(18,267,304)"
      ],
      [
        "보험금융손익",
        "905,296",
        "316,312",
        "1,024,131",
        "2,245,739"
      ],
      [
        "당기말 보험계약마진",
        "31,008,228",
        "5,805,897",
        "21,000,428",
        "57,814,553"
      ],
      [
        "당기 재보험서비스비용",
        "39,393,294",
        "18,059,867",
        "960,622,818",
        "1,018,075,979"
      ],
      [
        "장기",
        "3,789,203",
        "18,059,867",
        "19,580,001",
        "41,429,071"
      ],
      [
        "자동차",
        "-",
        "-",
        "7,127,957",
        "7,127,957"
      ],
      [
        "일반",
        "35,604,091",
        "-",
        "933,914,860",
        "969,518,951"
      ]
    ],
    "footnotes": [],
    "_source_xml": "20250313001346.xml"
  },
  {
    "caption": "당기와 전기 중 전환시점 적용 보험계약마진의 변동내역, 보험수익 및 재보험서비스비용은 다음과 같습니다.",
    "block_type": "mixed",
    "slice_label": "long_term",
    "slice_policy": "long_term",
    "mvp_candidate": true,
    "line_no": 65535,
    "score": 11,
    "reasons": [
      "caption: P&L keywords x2",
      "header: measurement columns x3",
      "rows: strong P&L stubs x3",
      "slice: long_term label present"
    ],
    "header": [
      [
        "구분",
        "수정소급법 적용 계약집합",
        "공정가치법 적용 계약집합",
        "그 외 계약집합",
        "합계"
      ]
    ],
    "rows": [
      [
        "보험계약",
        "",
        "",
        "",
        ""
      ],
      [
        "보험계약마진",
        "",
        "",
        "",
        ""
      ],
      [
        "전기말 보험계약마진",
        "4,773,487,276",
        "1,843,262,769",
        "1,734,787,218",
        "8,351,537,263"
      ],
      [
        "미래서비스와 관련된 변동",
        "(434,047,147)",
        "347,884,080",
        "1,493,809,496",
        "1,407,646,429"
      ],
      [
        "- 보험계약마진을 조정하는 추정치의 변동분",
        "(434,047,147)",
        "347,884,080",
        "(185,427,389)",
        "(271,590,456)"
      ],
      [
        "- 해당 기간에 처음 인식한 계약의 효과",
        "-",
        "-",
        "1,679,236,885",
        "1,679,236,885"
      ],
      [
        "당기서비스와 관련된 변동",
        "(406,585,044)",
        "(160,766,964)",
        "(313,192,835)",
        "(880,544,843)"
      ],
      [
        "- 서비스의 이전을 반영하기 위해 당기손익으로 인식한 보험계약마진 금액",
        "(406,585,044)",
        "(160,766,964)",
        "(313,192,835)",
        "(880,544,843)"
      ],
      [
        "보험금융손익",
        "109,207,676",
        "46,190,858",
        "108,233,756",
        "263,632,290"
      ],
      [
        "당기말 보험계약마진",
        "4,042,062,761",
        "2,076,570,743",
        "3,023,637,635",
        "9,142,271,139"
      ],
      [
        "당기 보험수익",
        "2,733,993,435",
        "3,033,893,242",
        "7,357,871,508",
        "13,125,758,185"
      ],
      [
        "장기",
        "2,521,873,317",
        "3,033,893,242",
        "1,369,542,114",
        "6,925,308,673"
      ],
      [
        "자동차",
        "22,542,237",
        "-",
        "4,216,631,959",
        "4,239,174,196"
      ],
      [
        "일반",
        "189,577,881",
        "-",
        "1,771,697,435",
        "1,961,275,316"
      ],
      [
        "출재보험계약",
        "",
        "",
        "",
        ""
      ],
      [
        "보험계약마진",
        "",
        "",
        "",
        ""
      ],
      [
        "전기말 보험계약마진",
        "28,637,189",
        "3,071,373",
        "388,847",
        "32,097,409"
      ],
      [
        "미래서비스와 관련된 변동",
        "4,647,992",
        "11,144,152",
        "22,346,294",
        "38,138,438"
      ],
      [
        "- 보험계약마진을 조정하는 추정치의 변동분",
        "4,647,992",
        "11,144,152",
        "22,532,905",
        "38,325,049"
      ],
      [
        "- 해당 기간에 처음 인식한 계약의 효과",
        "-",
        "-",
        "(186,611)",
        "(186,611)"
      ],
      [
        "당기서비스와 관련된 변동",
        "(3,368,533)",
        "(805,034)",
        "(3,515,595)",
        "(7,689,162)"
      ],
      [
        "- 서비스의 이전을 반영하기 위해 당기손익으로 인식한 보험계약마진 금액",
        "(3,368,533)",
        "(805,034)",
        "(3,515,595)",
        "(7,689,162)"
      ],
      [
        "보험금융손익",
        "907,510",
        "82,528",
        "181,126",
        "1,171,164"
      ],
      [
        "당기말 보험계약마진",
        "30,824,158",
        "13,493,019",
        "19,400,672",
        "63,717,849"
      ],
      [
        "당기 재보험서비스비용",
        "93,071,169",
        "22,320,521",
        "876,709,038",
        "992,100,728"
      ],
      [
        "장기",
        "4,024,688",
        "22,320,521",
        "4,173,151",
        "30,518,360"
      ],
      [
        "자동차",
        "-",
        "-",
        "5,528,107",
        "5,528,107"
      ],
      [
        "일반",
        "89,046,481",
        "-",
        "867,007,780",
        "956,054,261"
      ]
    ],
    "footnotes": [],
    "_source_xml": "20250313001346.xml"
  },
  {
    "caption": "당기 및 전기 중 보험계약 및 재보험계약에 대해 인식한 보험수익 및 재보험서비스비용의 내역은 다음과 같습니다.",
    "block_type": "mixed",
    "slice_label": "long_term",
    "slice_policy": "long_term",
    "mvp_candidate": true,
    "line_no": 30308,
    "score": 10,
    "reasons": [
      "caption: P&L keywords x2",
      "header: 1 measurement column",
      "rows: strong P&L stubs x3",
      "slice: long_term via non-PAA/GMM proxy"
    ],
    "header": [
      [
        "구 분",
        "장기",
        "자동차",
        "일반",
        "합계"
      ]
    ],
    "rows": [
      [
        "보험수익",
        "",
        "",
        "",
        ""
      ],
      [
        "예상보험금 및 보험서비스비용",
        "5,746,509,611",
        "-",
        "-",
        "5,746,509,611"
      ],
      [
        "위험조정변동",
        "132,912,992",
        "-",
        "-",
        "132,912,992"
      ],
      [
        "보험계약마진상각",
        "951,101,760",
        "-",
        "-",
        "951,101,760"
      ],
      [
        "손실요소배분",
        "(224,942,177)",
        "-",
        "-",
        "(224,942,177)"
      ],
      [
        "보험취득현금흐름상각",
        "875,811,972",
        "-",
        "-",
        "875,811,972"
      ],
      [
        "보험료배분접근법적용수익",
        "-",
        "4,178,678,299",
        "2,053,389,255",
        "6,232,067,554"
      ],
      [
        "합 계",
        "7,481,394,158",
        "4,178,678,299",
        "2,053,389,255",
        "13,713,461,712"
      ],
      [
        "재보험서비스비용",
        "",
        "",
        "",
        ""
      ],
      [
        "예상출재보험금 및 수입손해조사비",
        "15,409,680",
        "-",
        "-",
        "15,409,680"
      ],
      [
        "위험조정변동",
        "458,857",
        "-",
        "-",
        "458,857"
      ],
      [
        "보험계약마진상각",
        "18,267,303",
        "-",
        "-",
        "18,267,303"
      ],
      [
        "손실회수배분",
        "(221,323)",
        "-",
        "-",
        "(221,323)"
      ],
      [
        "출재보험료경험조정",
        "(5,359,709)",
        "-",
        "-",
        "(5,359,709)"
      ],
      [
        "출재투자요소경험조정",
        "227,723",
        "-",
        "-",
        "227,723"
      ],
      [
        "보험료배분접근법적용비용",
        "12,646,540",
        "7,127,957",
        "968,340,455",
        "988,114,952"
      ],
      [
        "합 계",
        "41,429,071",
        "7,127,957",
        "968,340,455",
        "1,016,897,483"
      ]
    ],
    "footnotes": [],
    "_source_xml": "20250313001346.xml"
  },
  {
    "caption": "당기 및 전기 중 보험계약 및 재보험계약에 대해 인식한 보험수익 및 재보험서비스비용의 내역은 다음과 같습니다.",
    "block_type": "mixed",
    "slice_label": "long_term",
    "slice_policy": "long_term",
    "mvp_candidate": true,
    "line_no": 30485,
    "score": 10,
    "reasons": [
      "caption: P&L keywords x2",
      "header: 1 measurement column",
      "rows: strong P&L stubs x3",
      "slice: long_term via non-PAA/GMM proxy"
    ],
    "header": [
      [
        "구 분",
        "장기",
        "자동차",
        "일반",
        "합계"
      ]
    ],
    "rows": [
      [
        "보험수익",
        "",
        "",
        "",
        ""
      ],
      [
        "예상보험금 및 보험서비스비용",
        "5,317,285,076",
        "-",
        "-",
        "5,317,285,076"
      ],
      [
        "위험조정변동",
        "130,628,669",
        "-",
        "-",
        "130,628,669"
      ],
      [
        "보험계약마진상각",
        "880,544,842",
        "-",
        "-",
        "880,544,842"
      ],
      [
        "손실요소배분",
        "(144,897,740)",
        "-",
        "-",
        "(144,897,740)"
      ],
      [
        "보험취득현금흐름상각",
        "741,747,826",
        "-",
        "-",
        "741,747,826"
      ],
      [
        "보험료배분접근법적용수익",
        "-",
        "4,239,174,196",
        "1,959,755,431",
        "6,198,929,626"
      ],
      [
        "합 계",
        "6,925,308,672",
        "4,239,174,196",
        "1,959,755,431",
        "13,124,238,299"
      ],
      [
        "재보험서비스비용",
        "",
        "",
        "",
        ""
      ],
      [
        "예상출재보험금 및 수입손해조사비",
        "14,683,693",
        "-",
        "-",
        "14,683,693"
      ],
      [
        "위험조정변동",
        "583,627",
        "-",
        "-",
        "583,627"
      ],
      [
        "보험계약마진상각",
        "7,689,161",
        "-",
        "-",
        "7,689,161"
      ],
      [
        "손실회수배분",
        "(60,262)",
        "-",
        "-",
        "(60,262)"
      ],
      [
        "출재보험료경험조정",
        "2,059,279",
        "-",
        "-",
        "2,059,279"
      ],
      [
        "출재투자요소경험조정",
        "(2,267,716)",
        "-",
        "-",
        "(2,267,716)"
      ],
      [
        "보험료배분접근법적용비용",
        "7,830,578",
        "5,528,107",
        "956,054,261",
        "969,412,946"
      ],
      [
        "합 계",
        "30,518,360",
        "5,528,107",
        "956,054,261",
        "992,100,728"
      ]
    ],
    "footnotes": [],
    "_source_xml": "20250313001346.xml"
  },
  {
    "caption": "당기 및 전기 중 보험계약 및 재보험계약에 대해 인식한 보험수익 및 재보험서비스비용의 내역은 다음과 같습니다.",
    "block_type": "mixed",
    "slice_label": "long_term",
    "slice_policy": "long_term",
    "mvp_candidate": true,
    "line_no": 65535,
    "score": 10,
    "reasons": [
      "caption: P&L keywords x2",
      "header: 1 measurement column",
      "rows: strong P&L stubs x3",
      "slice: long_term via non-PAA/GMM proxy"
    ],
    "header": [
      [
        "구 분",
        "장기",
        "자동차",
        "일반",
        "합계"
      ]
    ],
    "rows": [
      [
        "보험수익",
        "",
        "",
        "",
        ""
      ],
      [
        "예상보험금 및 보험서비스비용",
        "5,746,509,611",
        "-",
        "-",
        "5,746,509,611"
      ],
      [
        "위험조정변동",
        "132,912,992",
        "-",
        "-",
        "132,912,992"
      ],
      [
        "보험계약마진상각",
        "951,101,760",
        "-",
        "-",
        "951,101,760"
      ],
      [
        "손실요소배분",
        "(224,942,177)",
        "-",
        "-",
        "(224,942,177)"
      ],
      [
        "보험취득현금흐름상각",
        "875,811,972",
        "-",
        "-",
        "875,811,972"
      ],
      [
        "보험료배분접근법적용수익",
        "-",
        "4,178,678,299",
        "2,054,937,615",
        "6,233,615,914"
      ],
      [
        "합 계",
        "7,481,394,158",
        "4,178,678,299",
        "2,054,937,615",
        "13,715,010,072"
      ],
      [
        "재보험서비스비용",
        "",
        "",
        "",
        ""
      ],
      [
        "예상출재보험금 및 수입손해조사비",
        "15,409,680",
        "-",
        "-",
        "15,409,680"
      ],
      [
        "위험조정변동",
        "458,857",
        "-",
        "-",
        "458,857"
      ],
      [
        "보험계약마진상각",
        "18,267,303",
        "-",
        "-",
        "18,267,303"
      ],
      [
        "손실회수배분",
        "(221,323)",
        "-",
        "-",
        "(221,323)"
      ],
      [
        "출재보험료 경험조정",
        "(5,359,709)",
        "-",
        "-",
        "(5,359,709)"
      ],
      [
        "출재투자요소 경험조정",
        "227,723",
        "-",
        "-",
        "227,723"
      ],
      [
        "보험료배분접근법적용비용",
        "12,646,540",
        "7,127,957",
        "969,518,950",
        "989,293,447"
      ],
      [
        "합 계",
        "41,429,071",
        "7,127,957",
        "969,518,950",
        "1,018,075,978"
      ]
    ],
    "footnotes": [],
    "_source_xml": "20250313001346.xml"
  },
  {
    "caption": "당기 및 전기 중 보험계약 및 재보험계약에 대해 인식한 보험수익 및 재보험서비스비용의 내역은 다음과 같습니다.",
    "block_type": "mixed",
    "slice_label": "long_term",
    "slice_policy": "long_term",
    "mvp_candidate": true,
    "line_no": 65535,
    "score": 10,
    "reasons": [
      "caption: P&L keywords x2",
      "header: 1 measurement column",
      "rows: strong P&L stubs x3",
      "slice: long_term via non-PAA/GMM proxy"
    ],
    "header": [
      [
        "구 분",
        "장기",
        "자동차",
        "일반",
        "합계"
      ]
    ],
    "rows": [
      [
        "보험수익",
        "",
        "",
        "",
        ""
      ],
      [
        "예상보험금 및 보험서비스비용",
        "5,317,285,076",
        "-",
        "-",
        "5,317,285,076"
      ],
      [
        "위험조정변동",
        "130,628,669",
        "-",
        "-",
        "130,628,669"
      ],
      [
        "보험계약마진상각",
        "880,544,842",
        "-",
        "-",
        "880,544,842"
      ],
      [
        "손실요소배분",
        "(144,897,740)",
        "-",
        "-",
        "(144,897,740)"
      ],
      [
        "보험취득현금흐름상각",
        "741,747,826",
        "-",
        "-",
        "741,747,826"
      ],
      [
        "보험료배분접근법적용수익",
        "-",
        "4,239,174,196",
        "1,961,275,316",
        "6,200,449,512"
      ],
      [
        "합 계",
        "6,925,308,673",
        "4,239,174,196",
        "1,961,275,316",
        "13,125,758,185"
      ],
      [
        "재보험서비스비용",
        "",
        "",
        "",
        ""
      ],
      [
        "예상출재보험금 및 수입손해조사비",
        "14,683,693",
        "-",
        "-",
        "14,683,693"
      ],
      [
        "위험조정변동",
        "583,627",
        "-",
        "-",
        "583,627"
      ],
      [
        "보험계약마진상각",
        "7,689,161",
        "-",
        "-",
        "7,689,161"
      ],
      [
        "손실회수배분",
        "(60,262)",
        "-",
        "-",
        "(60,262)"
      ],
      [
        "출재보험료 경험조정",
        "2,059,279",
        "-",
        "-",
        "2,059,279"
      ],
      [
        "출재투자요소 경험조정",
        "(2,267,716)",
        "-",
        "-",
        "(2,267,716)"
      ],
      [
        "보험료배분접근법적용비용",
        "7,830,578",
        "5,528,107",
        "956,054,261",
        "969,412,946"
      ],
      [
        "합 계",
        "30,518,360",
        "5,528,107",
        "956,054,261",
        "992,100,728"
      ]
    ],
    "footnotes": [],
    "_source_xml": "20250313001346.xml"
  },
  {
    "caption": "26. 보험계약 및 재보험계약(1) 보험계약부채 및 재보험계약자산의 변동당기 및 전기 중 현금흐름 및 당기손익과 기타포괄손익으로 인식한 장부금액의 변동은 다음과 같습니다. 1) 장기원수가. 당기",
    "block_type": "direct",
    "slice_label": "long_term",
    "slice_policy": "long_term",
    "mvp_candidate": true,
    "line_no": 31904,
    "score": 5,
    "reasons": [
      "header: 1 measurement column",
      "rows: strong P&L stubs x2",
      "slice: long_term label present"
    ],
    "header": [
      [
        "구분",
        "잔여보장부채",
        "발생사고부채",
        "합계"
      ],
      [
        "손실요소외",
        "손실요소",
        "최선추정",
        "위험조정"
      ]
    ],
    "rows": [
      [
        "기초보험계약부채",
        "22,079,298,247",
        "1,619,076,694",
        "2,213,355,436",
        "42,229,635",
        "25,953,960,012"
      ],
      [
        "기초보험계약자산",
        "-",
        "-",
        "-",
        "-",
        "-"
      ],
      [
        "기초순보험계약부채",
        "22,079,298,247",
        "1,619,076,694",
        "2,213,355,436",
        "42,229,635",
        "25,953,960,012"
      ],
      [
        "보험수익",
        "(7,481,394,159)",
        "-",
        "-",
        "-",
        "(7,481,394,159)"
      ],
      [
        "보험서비스비용",
        "897,379,455",
        "(276,719,282)",
        "5,911,716,948",
        "6,878,041",
        "6,539,255,162"
      ],
      [
        "실제보험금 및 보험서비스비용",
        "-",
        "(224,942,177)",
        "6,046,288,202",
        "66,716,254",
        "5,888,062,279"
      ],
      [
        "보험취득현금흐름상각",
        "875,811,972",
        "-",
        "-",
        "-",
        "875,811,972"
      ],
      [
        "발생사고부채 이행현금흐름 변동",
        "-",
        "-",
        "(134,571,254)",
        "(59,838,213)",
        "(194,409,467)"
      ],
      [
        "손실부담계약집합의 변동",
        "-",
        "(51,777,105)",
        "-",
        "-",
        "(51,777,105)"
      ],
      [
        "기타",
        "21,567,483",
        "-",
        "-",
        "-",
        "21,567,483"
      ],
      [
        "투자요소",
        "(2,978,721,221)",
        "-",
        "2,978,721,221",
        "-",
        "-"
      ],
      [
        "보험금융손익",
        "3,640,599,570",
        "76,890,989",
        "86,920,322",
        "-",
        "3,804,410,881"
      ],
      [
        "현금흐름",
        "9,098,956,470",
        "-",
        "(8,753,144,823)",
        "-",
        "345,811,647"
      ],
      [
        "수취한 보험료",
        "11,037,925,371",
        "-",
        "-",
        "-",
        "11,037,925,371"
      ],
      [
        "보험취득현금흐름",
        "(1,938,544,459)",
        "-",
        "-",
        "-",
        "(1,938,544,459)"
      ],
      [
        "보험금 및 보험서비스비용",
        "(424,442)",
        "-",
        "(8,803,350,165)",
        "-",
        "(8,803,774,607)"
      ],
      [
        "기타",
        "-",
        "-",
        "50,205,342",
        "-",
        "50,205,342"
      ],
      [
        "기말보험계약순부채",
        "25,256,118,362",
        "1,419,248,401",
        "2,437,569,104",
        "49,107,676",
        "29,162,043,543"
      ],
      [
        "기말보험계약부채",
        "25,256,118,362",
        "1,419,248,401",
        "2,437,569,104",
        "49,107,676",
        "29,162,043,543"
      ],
      [
        "기말보험계약자산",
        "-",
        "-",
        "-",
        "-",
        "-"
      ]
    ],
    "footnotes": [],
    "_source_xml": "20250313001346.xml"
  },
  {
    "caption": "26. 보험계약 및 재보험계약(1) 보험계약부채 및 재보험계약자산의 변동당기 및 전기 중 현금흐름 및 당기손익과 기타포괄손익으로 인식한 장부금액의 변동은 다음과 같습니다.1) 장기원수가. 당기",
    "block_type": "direct",
    "slice_label": "long_term",
    "slice_policy": "long_term",
    "mvp_candidate": true,
    "line_no": 65535,
    "score": 5,
    "reasons": [
      "header: 1 measurement column",
      "rows: strong P&L stubs x2",
      "slice: long_term label present"
    ],
    "header": [
      [
        "구분",
        "잔여보장부채",
        "발생사고부채",
        "합계"
      ],
      [
        "손실요소외",
        "손실요소",
        "최선추정",
        "위험조정"
      ]
    ],
    "rows": [
      [
        "기초보험계약부채",
        "22,079,298,247",
        "1,619,076,694",
        "2,213,355,436",
        "42,229,635",
        "25,953,960,012"
      ],
      [
        "기초보험계약자산",
        "-",
        "-",
        "-",
        "-",
        "-"
      ],
      [
        "기초순보험계약부채",
        "22,079,298,247",
        "1,619,076,694",
        "2,213,355,436",
        "42,229,635",
        "25,953,960,012"
      ],
      [
        "보험수익",
        "(7,481,394,159)",
        "-",
        "-",
        "-",
        "(7,481,394,159)"
      ],
      [
        "보험서비스비용",
        "897,379,455",
        "(276,719,282)",
        "5,932,955,457",
        "6,878,042",
        "6,560,493,672"
      ],
      [
        "실제보험금 및 보험서비스비용",
        "-",
        "(224,942,177)",
        "6,067,526,711",
        "66,716,255",
        "5,909,300,789"
      ],
      [
        "보험취득현금흐름상각",
        "875,811,972",
        "-",
        "-",
        "-",
        "875,811,972"
      ],
      [
        "발생사고부채 이행현금흐름 변동",
        "-",
        "-",
        "(134,571,254)",
        "(59,838,213)",
        "(194,409,467)"
      ],
      [
        "손실부담계약집합의 변동",
        "-",
        "(51,777,105)",
        "-",
        "-",
        "(51,777,105)"
      ],
      [
        "기타",
        "21,567,483",
        "-",
        "-",
        "-",
        "21,567,483"
      ],
      [
        "투자요소",
        "(2,978,721,221)",
        "-",
        "2,978,721,221",
        "-",
        "-"
      ],
      [
        "보험금융손익",
        "3,640,599,570",
        "76,890,989",
        "86,920,322",
        "-",
        "3,804,410,881"
      ],
      [
        "현금흐름",
        "9,098,956,470",
        "-",
        "(8,774,383,332)",
        "-",
        "324,573,138"
      ],
      [
        "수취한 보험료",
        "11,037,925,371",
        "-",
        "-",
        "-",
        "11,037,925,371"
      ],
      [
        "보험취득현금흐름",
        "(1,938,544,459)",
        "-",
        "-",
        "-",
        "(1,938,544,459)"
      ],
      [
        "보험금 및 보험서비스비용",
        "(424,442)",
        "-",
        "(8,824,588,674)",
        "-",
        "(8,825,013,116)"
      ],
      [
        "기타",
        "-",
        "-",
        "50,205,342",
        "-",
        "50,205,342"
      ],
      [
        "당기말보험계약순부채",
        "25,256,118,362",
        "1,419,248,401",
        "2,437,569,104",
        "49,107,677",
        "29,162,043,544"
      ],
      [
        "당기말보험계약부채",
        "25,256,118,362",
        "1,419,248,401",
        "2,437,569,104",
        "49,107,677",
        "29,162,043,544"
      ],
      [
        "당기말보험계약자산",
        "-",
        "-",
        "",
        "",
        ""
      ]
    ],
    "footnotes": [],
    "_source_xml": "20250313001346.xml"
  },
  {
    "caption": "당기와 전기 중 전환시점 적용 보험계약마진의 변동내역, 보험수익 및 재보험서비스비용은 다음과 같습니다.",
    "block_type": "mixed",
    "slice_label": "long_term",
    "slice_policy": "long_term",
    "mvp_candidate": true,
    "line_no": 22090,
    "score": 11,
    "reasons": [
      "caption: P&L keywords x2",
      "header: measurement columns x3",
      "rows: strong P&L stubs x3",
      "slice: long_term label present"
    ],
    "header": [
      [
        "구분",
        "수정소급법 적용 계약집합",
        "공정가치법 적용 계약집합",
        "그 외 계약집합",
        "합계"
      ]
    ],
    "rows": [
      [
        "보험계약",
        "",
        "",
        "",
        ""
      ],
      [
        "보험계약마진",
        "",
        "",
        "",
        ""
      ],
      [
        "전기말 보험계약마진",
        "4,042,062,762",
        "2,076,570,743",
        "3,023,637,636",
        "9,142,271,141"
      ],
      [
        "미래서비스와 관련된 변동",
        "(1,247,735,021)",
        "231,489,543",
        "809,101,521",
        "(207,143,957)"
      ],
      [
        "- 보험계약마진을 조정하는 추정치의 변동분",
        "(1,247,735,021)",
        "231,489,543",
        "(1,018,777,832)",
        "(2,035,023,310)"
      ],
      [
        "- 해당 기간에 처음 인식한 계약의 효과",
        "-",
        "-",
        "1,827,879,353",
        "1,827,879,353"
      ],
      [
        "당기서비스와 관련된 변동",
        "(333,525,682)",
        "(171,269,650)",
        "(446,306,428)",
        "(951,101,760)"
      ],
      [
        "- 서비스의 이전을 반영하기 위해 당기손익으로 인식한 보험계약마진 금액",
        "(333,525,682)",
        "(171,269,650)",
        "(446,306,428)",
        "(951,101,760)"
      ],
      [
        "보험금융손익",
        "101,719,750",
        "46,962,204",
        "172,779,885",
        "321,461,839"
      ],
      [
        "당기말 보험계약마진",
        "2,562,521,809",
        "2,183,752,840",
        "3,559,212,614",
        "8,305,487,263"
      ],
      [
        "당기 보험수익",
        "2,444,403,901",
        "2,890,876,548",
        "8,379,729,625",
        "13,715,010,074"
      ],
      [
        "장기",
        "2,344,840,554",
        "2,890,876,548",
        "2,245,677,057",
        "7,481,394,159"
      ],
      [
        "자동차",
        "12,517,690",
        "-",
        "4,166,160,610",
        "4,178,678,300"
      ],
      [
        "일반",
        "87,045,657",
        "-",
        "1,967,891,958",
        "2,054,937,615"
      ],
      [
        "출재보험계약",
        "",
        "",
        "",
        ""
      ],
      [
        "보험계약마진",
        "",
        "",
        "",
        ""
      ],
      [
        "전기말 보험계약마진",
        "30,824,158",
        "13,493,019",
        "19,400,672",
        "63,717,849"
      ],
      [
        "미래서비스와 관련된 변동",
        "2,939,785",
        "(2,141,157)",
        "9,319,641",
        "10,118,269"
      ],
      [
        "- 보험계약마진을 조정하는 추정치의 변동분",
        "2,939,785",
        "(2,141,157)",
        "2,393,363",
        "3,191,991"
      ],
      [
        "- 해당 기간에 처음 인식한 계약의 효과",
        "-",
        "-",
        "6,926,278",
        "6,926,278"
      ],
      [
        "당기서비스와 관련된 변동",
        "(3,661,011)",
        "(5,862,277)",
        "(8,744,016)",
        "(18,267,304)"
      ],
      [
        "- 서비스의 이전을 반영하기 위해 당기손익으로 인식한 보험계약마진 금액",
        "(3,661,011)",
        "(5,862,277)",
        "(8,744,016)",
        "(18,267,304)"
      ],
      [
        "보험금융손익",
        "905,296",
        "316,312",
        "1,024,131",
        "2,245,739"
      ],
      [
        "당기말 보험계약마진",
        "31,008,228",
        "5,805,897",
        "21,000,428",
        "57,814,553"
      ],
      [
        "당기 재보험서비스비용",
        "39,393,294",
        "18,059,867",
        "960,622,818",
        "1,018,075,979"
      ],
      [
        "장기",
        "3,789,203",
        "18,059,867",
        "19,580,001",
        "41,429,071"
      ],
      [
        "자동차",
        "-",
        "-",
        "7,127,957",
        "7,127,957"
      ],
      [
        "일반",
        "35,604,091",
        "-",
        "933,914,860",
        "969,518,951"
      ]
    ],
    "footnotes": [],
    "_source_xml": "20250313001346_00760.xml"
  },
  {
    "caption": "당기와 전기 중 전환시점 적용 보험계약마진의 변동내역, 보험수익 및 재보험서비스비용은 다음과 같습니다.",
    "block_type": "mixed",
    "slice_label": "long_term",
    "slice_policy": "long_term",
    "mvp_candidate": true,
    "line_no": 22355,
    "score": 11,
    "reasons": [
      "caption: P&L keywords x2",
      "header: measurement columns x3",
      "rows: strong P&L stubs x3",
      "slice: long_term label present"
    ],
    "header": [
      [
        "구분",
        "수정소급법 적용 계약집합",
        "공정가치법 적용 계약집합",
        "그 외 계약집합",
        "합계"
      ]
    ],
    "rows": [
      [
        "보험계약",
        "",
        "",
        "",
        ""
      ],
      [
        "보험계약마진",
        "",
        "",
        "",
        ""
      ],
      [
        "전기말 보험계약마진",
        "4,773,487,276",
        "1,843,262,769",
        "1,734,787,218",
        "8,351,537,263"
      ],
      [
        "미래서비스와 관련된 변동",
        "(434,047,147)",
        "347,884,080",
        "1,493,809,496",
        "1,407,646,429"
      ],
      [
        "- 보험계약마진을 조정하는 추정치의 변동분",
        "(434,047,147)",
        "347,884,080",
        "(185,427,389)",
        "(271,590,456)"
      ],
      [
        "- 해당 기간에 처음 인식한 계약의 효과",
        "-",
        "-",
        "1,679,236,885",
        "1,679,236,885"
      ],
      [
        "당기서비스와 관련된 변동",
        "(406,585,044)",
        "(160,766,964)",
        "(313,192,835)",
        "(880,544,843)"
      ],
      [
        "- 서비스의 이전을 반영하기 위해 당기손익으로 인식한 보험계약마진 금액",
        "(406,585,044)",
        "(160,766,964)",
        "(313,192,835)",
        "(880,544,843)"
      ],
      [
        "보험금융손익",
        "109,207,676",
        "46,190,858",
        "108,233,756",
        "263,632,290"
      ],
      [
        "당기말 보험계약마진",
        "4,042,062,761",
        "2,076,570,743",
        "3,023,637,635",
        "9,142,271,139"
      ],
      [
        "당기 보험수익",
        "2,733,993,435",
        "3,033,893,242",
        "7,357,871,508",
        "13,125,758,185"
      ],
      [
        "장기",
        "2,521,873,317",
        "3,033,893,242",
        "1,369,542,114",
        "6,925,308,673"
      ],
      [
        "자동차",
        "22,542,237",
        "-",
        "4,216,631,959",
        "4,239,174,196"
      ],
      [
        "일반",
        "189,577,881",
        "-",
        "1,771,697,435",
        "1,961,275,316"
      ],
      [
        "출재보험계약",
        "",
        "",
        "",
        ""
      ],
      [
        "보험계약마진",
        "",
        "",
        "",
        ""
      ],
      [
        "전기말 보험계약마진",
        "28,637,189",
        "3,071,373",
        "388,847",
        "32,097,409"
      ],
      [
        "미래서비스와 관련된 변동",
        "4,647,992",
        "11,144,152",
        "22,346,294",
        "38,138,438"
      ],
      [
        "- 보험계약마진을 조정하는 추정치의 변동분",
        "4,647,992",
        "11,144,152",
        "22,532,905",
        "38,325,049"
      ],
      [
        "- 해당 기간에 처음 인식한 계약의 효과",
        "-",
        "-",
        "(186,611)",
        "(186,611)"
      ],
      [
        "당기서비스와 관련된 변동",
        "(3,368,533)",
        "(805,034)",
        "(3,515,595)",
        "(7,689,162)"
      ],
      [
        "- 서비스의 이전을 반영하기 위해 당기손익으로 인식한 보험계약마진 금액",
        "(3,368,533)",
        "(805,034)",
        "(3,515,595)",
        "(7,689,162)"
      ],
      [
        "보험금융손익",
        "907,510",
        "82,528",
        "181,126",
        "1,171,164"
      ],
      [
        "당기말 보험계약마진",
        "30,824,158",
        "13,493,019",
        "19,400,672",
        "63,717,849"
      ],
      [
        "당기 재보험서비스비용",
        "93,071,169",
        "22,320,521",
        "876,709,038",
        "992,100,728"
      ],
      [
        "장기",
        "4,024,688",
        "22,320,521",
        "4,173,151",
        "30,518,360"
      ],
      [
        "자동차",
        "-",
        "-",
        "5,528,107",
        "5,528,107"
      ],
      [
        "일반",
        "89,046,481",
        "-",
        "867,007,780",
        "956,054,261"
      ]
    ],
    "footnotes": [],
    "_source_xml": "20250313001346_00760.xml"
  },
  {
    "caption": "당기 및 전기 중 보험계약 및 재보험계약에 대해 인식한 보험수익 및 재보험서비스비용의 내역은 다음과 같습니다.",
    "block_type": "mixed",
    "slice_label": "long_term",
    "slice_policy": "long_term",
    "mvp_candidate": true,
    "line_no": 16634,
    "score": 10,
    "reasons": [
      "caption: P&L keywords x2",
      "header: 1 measurement column",
      "rows: strong P&L stubs x3",
      "slice: long_term via non-PAA/GMM proxy"
    ],
    "header": [
      [
        "구 분",
        "장기",
        "자동차",
        "일반",
        "합계"
      ]
    ],
    "rows": [
      [
        "보험수익",
        "",
        "",
        "",
        ""
      ],
      [
        "예상보험금 및 보험서비스비용",
        "5,746,509,611",
        "-",
        "-",
        "5,746,509,611"
      ],
      [
        "위험조정변동",
        "132,912,992",
        "-",
        "-",
        "132,912,992"
      ],
      [
        "보험계약마진상각",
        "951,101,760",
        "-",
        "-",
        "951,101,760"
      ],
      [
        "손실요소배분",
        "(224,942,177)",
        "-",
        "-",
        "(224,942,177)"
      ],
      [
        "보험취득현금흐름상각",
        "875,811,972",
        "-",
        "-",
        "875,811,972"
      ],
      [
        "보험료배분접근법적용수익",
        "-",
        "4,178,678,299",
        "2,054,937,615",
        "6,233,615,914"
      ],
      [
        "합 계",
        "7,481,394,158",
        "4,178,678,299",
        "2,054,937,615",
        "13,715,010,072"
      ],
      [
        "재보험서비스비용",
        "",
        "",
        "",
        ""
      ],
      [
        "예상출재보험금 및 수입손해조사비",
        "15,409,680",
        "-",
        "-",
        "15,409,680"
      ],
      [
        "위험조정변동",
        "458,857",
        "-",
        "-",
        "458,857"
      ],
      [
        "보험계약마진상각",
        "18,267,303",
        "-",
        "-",
        "18,267,303"
      ],
      [
        "손실회수배분",
        "(221,323)",
        "-",
        "-",
        "(221,323)"
      ],
      [
        "출재보험료 경험조정",
        "(5,359,709)",
        "-",
        "-",
        "(5,359,709)"
      ],
      [
        "출재투자요소 경험조정",
        "227,723",
        "-",
        "-",
        "227,723"
      ],
      [
        "보험료배분접근법적용비용",
        "12,646,540",
        "7,127,957",
        "969,518,950",
        "989,293,447"
      ],
      [
        "합 계",
        "41,429,071",
        "7,127,957",
        "969,518,950",
        "1,018,075,978"
      ]
    ],
    "footnotes": [],
    "_source_xml": "20250313001346_00760.xml"
  },
  {
    "caption": "당기 및 전기 중 보험계약 및 재보험계약에 대해 인식한 보험수익 및 재보험서비스비용의 내역은 다음과 같습니다.",
    "block_type": "mixed",
    "slice_label": "long_term",
    "slice_policy": "long_term",
    "mvp_candidate": true,
    "line_no": 16811,
    "score": 10,
    "reasons": [
      "caption: P&L keywords x2",
      "header: 1 measurement column",
      "rows: strong P&L stubs x3",
      "slice: long_term via non-PAA/GMM proxy"
    ],
    "header": [
      [
        "구 분",
        "장기",
        "자동차",
        "일반",
        "합계"
      ]
    ],
    "rows": [
      [
        "보험수익",
        "",
        "",
        "",
        ""
      ],
      [
        "예상보험금 및 보험서비스비용",
        "5,317,285,076",
        "-",
        "-",
        "5,317,285,076"
      ],
      [
        "위험조정변동",
        "130,628,669",
        "-",
        "-",
        "130,628,669"
      ],
      [
        "보험계약마진상각",
        "880,544,842",
        "-",
        "-",
        "880,544,842"
      ],
      [
        "손실요소배분",
        "(144,897,740)",
        "-",
        "-",
        "(144,897,740)"
      ],
      [
        "보험취득현금흐름상각",
        "741,747,826",
        "-",
        "-",
        "741,747,826"
      ],
      [
        "보험료배분접근법적용수익",
        "-",
        "4,239,174,196",
        "1,961,275,316",
        "6,200,449,512"
      ],
      [
        "합 계",
        "6,925,308,673",
        "4,239,174,196",
        "1,961,275,316",
        "13,125,758,185"
      ],
      [
        "재보험서비스비용",
        "",
        "",
        "",
        ""
      ],
      [
        "예상출재보험금 및 수입손해조사비",
        "14,683,693",
        "-",
        "-",
        "14,683,693"
      ],
      [
        "위험조정변동",
        "583,627",
        "-",
        "-",
        "583,627"
      ],
      [
        "보험계약마진상각",
        "7,689,161",
        "-",
        "-",
        "7,689,161"
      ],
      [
        "손실회수배분",
        "(60,262)",
        "-",
        "-",
        "(60,262)"
      ],
      [
        "출재보험료 경험조정",
        "2,059,279",
        "-",
        "-",
        "2,059,279"
      ],
      [
        "출재투자요소 경험조정",
        "(2,267,716)",
        "-",
        "-",
        "(2,267,716)"
      ],
      [
        "보험료배분접근법적용비용",
        "7,830,578",
        "5,528,107",
        "956,054,261",
        "969,412,946"
      ],
      [
        "합 계",
        "30,518,360",
        "5,528,107",
        "956,054,261",
        "992,100,728"
      ]
    ],
    "footnotes": [],
    "_source_xml": "20250313001346_00760.xml"
  },
  {
    "caption": "26. 보험계약 및 재보험계약(1) 보험계약부채 및 재보험계약자산의 변동당기 및 전기 중 현금흐름 및 당기손익과 기타포괄손익으로 인식한 장부금액의 변동은 다음과 같습니다.1) 장기원수가. 당기",
    "block_type": "direct",
    "slice_label": "long_term",
    "slice_policy": "long_term",
    "mvp_candidate": true,
    "line_no": 18238,
    "score": 5,
    "reasons": [
      "header: 1 measurement column",
      "rows: strong P&L stubs x2",
      "slice: long_term label present"
    ],
    "header": [
      [
        "구분",
        "잔여보장부채",
        "발생사고부채",
        "합계"
      ],
      [
        "손실요소외",
        "손실요소",
        "최선추정",
        "위험조정"
      ]
    ],
    "rows": [
      [
        "기초보험계약부채",
        "22,079,298,247",
        "1,619,076,694",
        "2,213,355,436",
        "42,229,635",
        "25,953,960,012"
      ],
      [
        "기초보험계약자산",
        "-",
        "-",
        "-",
        "-",
        "-"
      ],
      [
        "기초순보험계약부채",
        "22,079,298,247",
        "1,619,076,694",
        "2,213,355,436",
        "42,229,635",
        "25,953,960,012"
      ],
      [
        "보험수익",
        "(7,481,394,159)",
        "-",
        "-",
        "-",
        "(7,481,394,159)"
      ],
      [
        "보험서비스비용",
        "897,379,455",
        "(276,719,282)",
        "5,932,955,457",
        "6,878,042",
        "6,560,493,672"
      ],
      [
        "실제보험금 및 보험서비스비용",
        "-",
        "(224,942,177)",
        "6,067,526,711",
        "66,716,255",
        "5,909,300,789"
      ],
      [
        "보험취득현금흐름상각",
        "875,811,972",
        "-",
        "-",
        "-",
        "875,811,972"
      ],
      [
        "발생사고부채 이행현금흐름 변동",
        "-",
        "-",
        "(134,571,254)",
        "(59,838,213)",
        "(194,409,467)"
      ],
      [
        "손실부담계약집합의 변동",
        "-",
        "(51,777,105)",
        "-",
        "-",
        "(51,777,105)"
      ],
      [
        "기타",
        "21,567,483",
        "-",
        "-",
        "-",
        "21,567,483"
      ],
      [
        "투자요소",
        "(2,978,721,221)",
        "-",
        "2,978,721,221",
        "-",
        "-"
      ],
      [
        "보험금융손익",
        "3,640,599,570",
        "76,890,989",
        "86,920,322",
        "-",
        "3,804,410,881"
      ],
      [
        "현금흐름",
        "9,098,956,470",
        "-",
        "(8,774,383,332)",
        "-",
        "324,573,138"
      ],
      [
        "수취한 보험료",
        "11,037,925,371",
        "-",
        "-",
        "-",
        "11,037,925,371"
      ],
      [
        "보험취득현금흐름",
        "(1,938,544,459)",
        "-",
        "-",
        "-",
        "(1,938,544,459)"
      ],
      [
        "보험금 및 보험서비스비용",
        "(424,442)",
        "-",
        "(8,824,588,674)",
        "-",
        "(8,825,013,116)"
      ],
      [
        "기타",
        "-",
        "-",
        "50,205,342",
        "-",
        "50,205,342"
      ],
      [
        "당기말보험계약순부채",
        "25,256,118,362",
        "1,419,248,401",
        "2,437,569,104",
        "49,107,677",
        "29,162,043,544"
      ],
      [
        "당기말보험계약부채",
        "25,256,118,362",
        "1,419,248,401",
        "2,437,569,104",
        "49,107,677",
        "29,162,043,544"
      ],
      [
        "당기말보험계약자산",
        "-",
        "-",
        "",
        "",
        ""
      ]
    ],
    "footnotes": [],
    "_source_xml": "20250313001346_00760.xml"
  },
  {
    "caption": "당기와 전기 중 전환시점 적용 보험계약마진의 변동내역, 보험수익 및 재보험서비스비용은 다음과 같습니다.",
    "block_type": "mixed",
    "slice_label": "long_term",
    "slice_policy": "long_term",
    "mvp_candidate": true,
    "line_no": 24992,
    "score": 11,
    "reasons": [
      "caption: P&L keywords x2",
      "header: measurement columns x3",
      "rows: strong P&L stubs x3",
      "slice: long_term label present"
    ],
    "header": [
      [
        "구분",
        "수정소급법 적용 계약집합",
        "공정가치법 적용 계약집합",
        "그 외 계약집합",
        "합계"
      ]
    ],
    "rows": [
      [
        "보험계약",
        "",
        "",
        "",
        ""
      ],
      [
        "보험계약마진",
        "",
        "",
        "",
        ""
      ],
      [
        "전기말 보험계약마진",
        "4,042,062,762",
        "2,076,570,743",
        "3,023,637,636",
        "9,142,271,141"
      ],
      [
        "미래서비스와 관련된 변동",
        "(1,247,735,021)",
        "231,489,543",
        "809,101,521",
        "(207,143,957)"
      ],
      [
        "- 보험계약마진을 조정하는 추정치의 변동분",
        "(1,247,735,021)",
        "231,489,543",
        "(1,018,777,832)",
        "(2,035,023,310)"
      ],
      [
        "- 해당 기간에 처음 인식한 계약의 효과",
        "-",
        "-",
        "1,827,879,353",
        "1,827,879,353"
      ],
      [
        "당기서비스와 관련된 변동",
        "(333,525,682)",
        "(171,269,650)",
        "(446,306,428)",
        "(951,101,760)"
      ],
      [
        "- 서비스의 이전을 반영하기 위해 당기손익으로 인식한 보험계약마진 금액",
        "(333,525,682)",
        "(171,269,650)",
        "(446,306,428)",
        "(951,101,760)"
      ],
      [
        "보험금융손익",
        "101,719,750",
        "46,962,204",
        "172,779,885",
        "321,461,839"
      ],
      [
        "당기말 보험계약마진",
        "2,562,521,809",
        "2,183,752,840",
        "3,559,212,614",
        "8,305,487,263"
      ],
      [
        "당기 보험수익",
        "2,444,403,901",
        "2,890,876,548",
        "8,378,181,263",
        "13,713,461,712"
      ],
      [
        "장기",
        "2,344,840,554",
        "2,890,876,548",
        "2,245,677,057",
        "7,481,394,159"
      ],
      [
        "자동차",
        "12,517,690",
        "-",
        "4,166,160,610",
        "4,178,678,300"
      ],
      [
        "일반",
        "87,045,657",
        "-",
        "1,966,343,596",
        "2,053,389,253"
      ],
      [
        "출재보험계약",
        "",
        "",
        "",
        ""
      ],
      [
        "보험계약마진",
        "",
        "",
        "",
        ""
      ],
      [
        "전기말 보험계약마진",
        "30,824,158",
        "13,493,019",
        "19,400,672",
        "63,717,849"
      ],
      [
        "미래서비스와 관련된 변동",
        "2,939,785",
        "(2,141,157)",
        "9,319,641",
        "10,118,269"
      ],
      [
        "- 보험계약마진을 조정하는 추정치의 변동분",
        "2,939,785",
        "(2,141,157)",
        "2,393,363",
        "3,191,991"
      ],
      [
        "- 해당 기간에 처음 인식한 계약의 효과",
        "-",
        "-",
        "6,926,278",
        "6,926,278"
      ],
      [
        "당기서비스와 관련된 변동",
        "(3,661,011)",
        "(5,862,277)",
        "(8,744,016)",
        "(18,267,304)"
      ],
      [
        "- 서비스의 이전을 반영하기 위해 당기손익으로 인식한 보험계약마진 금액",
        "(3,661,011)",
        "(5,862,277)",
        "(8,744,016)",
        "(18,267,304)"
      ],
      [
        "보험금융손익",
        "905,296",
        "316,312",
        "1,024,131",
        "2,245,739"
      ],
      [
        "당기말 보험계약마진",
        "31,008,228",
        "5,805,897",
        "21,000,428",
        "57,814,553"
      ],
      [
        "당기 재보험서비스비용",
        "39,393,294",
        "18,059,867",
        "959,444,323",
        "1,016,897,484"
      ],
      [
        "장기",
        "3,789,203",
        "18,059,867",
        "19,580,001",
        "41,429,071"
      ],
      [
        "자동차",
        "-",
        "-",
        "7,127,957",
        "7,127,957"
      ],
      [
        "일반",
        "35,604,091",
        "-",
        "932,736,365",
        "968,340,456"
      ]
    ],
    "footnotes": [],
    "_source_xml": "20250313001346_00761.xml"
  },
  {
    "caption": "당기와 전기 중 전환시점 적용 보험계약마진의 변동내역, 보험수익 및 재보험서비스비용은 다음과 같습니다.",
    "block_type": "mixed",
    "slice_label": "long_term",
    "slice_policy": "long_term",
    "mvp_candidate": true,
    "line_no": 25257,
    "score": 11,
    "reasons": [
      "caption: P&L keywords x2",
      "header: measurement columns x3",
      "rows: strong P&L stubs x3",
      "slice: long_term label present"
    ],
    "header": [
      [
        "구분",
        "수정소급법 적용 계약집합",
        "공정가치법 적용 계약집합",
        "그 외 계약집합",
        "합계"
      ]
    ],
    "rows": [
      [
        "보험계약",
        "",
        "",
        "",
        ""
      ],
      [
        "보험계약마진",
        "",
        "",
        "",
        ""
      ],
      [
        "전전기말 보험계약마진",
        "4,773,487,276",
        "1,843,262,769",
        "1,734,787,218",
        "8,351,537,263"
      ],
      [
        "미래서비스와 관련된 변동",
        "(434,047,147)",
        "347,884,080",
        "1,493,809,496",
        "1,407,646,429"
      ],
      [
        "- 보험계약마진을 조정하는 추정치의 변동분",
        "(434,047,147)",
        "347,884,080",
        "(185,427,389)",
        "(271,590,456)"
      ],
      [
        "- 해당 기간에 처음 인식한 계약의 효과",
        "-",
        "-",
        "1,679,236,885",
        "1,679,236,885"
      ],
      [
        "당기서비스와 관련된 변동",
        "(406,585,044)",
        "(160,766,964)",
        "(313,192,835)",
        "(880,544,843)"
      ],
      [
        "- 서비스의 이전을 반영하기 위해 당기손익으로 인식한 보험계약마진 금액",
        "(406,585,044)",
        "(160,766,964)",
        "(313,192,835)",
        "(880,544,843)"
      ],
      [
        "보험금융손익",
        "109,207,676",
        "46,190,858",
        "108,233,756",
        "263,632,290"
      ],
      [
        "전기말 보험계약마진",
        "4,042,062,761",
        "2,076,570,743",
        "3,023,637,635",
        "9,142,271,139"
      ],
      [
        "전기 보험수익",
        "2,733,993,435",
        "3,033,893,242",
        "7,356,351,623",
        "13,124,238,300"
      ],
      [
        "장기",
        "2,521,873,317",
        "3,033,893,242",
        "1,369,542,114",
        "6,925,308,673"
      ],
      [
        "자동차",
        "22,542,237",
        "-",
        "4,216,631,959",
        "4,239,174,196"
      ],
      [
        "일반",
        "189,577,881",
        "-",
        "1,770,177,550",
        "1,959,755,431"
      ],
      [
        "출재보험계약",
        "",
        "",
        "",
        ""
      ],
      [
        "보험계약마진",
        "",
        "",
        "",
        ""
      ],
      [
        "전전기말 보험계약마진",
        "28,637,189",
        "3,071,373",
        "388,847",
        "32,097,409"
      ],
      [
        "미래서비스와 관련된 변동",
        "4,647,992",
        "11,144,152",
        "22,346,294",
        "38,138,438"
      ],
      [
        "- 보험계약마진을 조정하는 추정치의 변동분",
        "4,647,992",
        "11,144,152",
        "22,532,905",
        "38,325,049"
      ],
      [
        "- 해당 기간에 처음 인식한 계약의 효과",
        "-",
        "-",
        "(186,611)",
        "(186,611)"
      ],
      [
        "당기서비스와 관련된 변동",
        "(3,368,533)",
        "(805,034)",
        "(3,515,595)",
        "(7,689,162)"
      ],
      [
        "- 서비스의 이전을 반영하기 위해 당기손익으로 인식한 보험계약마진 금액",
        "(3,368,533)",
        "(805,034)",
        "(3,515,595)",
        "(7,689,162)"
      ],
      [
        "보험금융손익",
        "907,510",
        "82,528",
        "181,126",
        "1,171,164"
      ],
      [
        "전기말 보험계약마진",
        "30,824,158",
        "13,493,019",
        "19,400,672",
        "63,717,849"
      ],
      [
        "전기 재보험서비스비용",
        "93,071,169",
        "22,320,521",
        "876,709,038",
        "992,100,728"
      ],
      [
        "장기",
        "4,024,688",
        "22,320,521",
        "4,173,151",
        "30,518,360"
      ],
      [
        "자동차",
        "-",
        "-",
        "5,528,107",
        "5,528,107"
      ],
      [
        "일반",
        "89,046,481",
        "-",
        "867,007,780",
        "956,054,261"
      ]
    ],
    "footnotes": [],
    "_source_xml": "20250313001346_00761.xml"
  },
  {
    "caption": "당기 및 전기 중 보험계약 및 재보험계약에 대해 인식한 보험수익 및 재보험서비스비용의 내역은 다음과 같습니다.",
    "block_type": "mixed",
    "slice_label": "long_term",
    "slice_policy": "long_term",
    "mvp_candidate": true,
    "line_no": 19548,
    "score": 10,
    "reasons": [
      "caption: P&L keywords x2",
      "header: 1 measurement column",
      "rows: strong P&L stubs x3",
      "slice: long_term via non-PAA/GMM proxy"
    ],
    "header": [
      [
        "구 분",
        "장기",
        "자동차",
        "일반",
        "합계"
      ]
    ],
    "rows": [
      [
        "보험수익",
        "",
        "",
        "",
        ""
      ],
      [
        "예상보험금 및 보험서비스비용",
        "5,746,509,611",
        "-",
        "-",
        "5,746,509,611"
      ],
      [
        "위험조정변동",
        "132,912,992",
        "-",
        "-",
        "132,912,992"
      ],
      [
        "보험계약마진상각",
        "951,101,760",
        "-",
        "-",
        "951,101,760"
      ],
      [
        "손실요소배분",
        "(224,942,177)",
        "-",
        "-",
        "(224,942,177)"
      ],
      [
        "보험취득현금흐름상각",
        "875,811,972",
        "-",
        "-",
        "875,811,972"
      ],
      [
        "보험료배분접근법적용수익",
        "-",
        "4,178,678,299",
        "2,053,389,255",
        "6,232,067,554"
      ],
      [
        "합 계",
        "7,481,394,158",
        "4,178,678,299",
        "2,053,389,255",
        "13,713,461,712"
      ],
      [
        "재보험서비스비용",
        "",
        "",
        "",
        ""
      ],
      [
        "예상출재보험금 및 수입손해조사비",
        "15,409,680",
        "-",
        "-",
        "15,409,680"
      ],
      [
        "위험조정변동",
        "458,857",
        "-",
        "-",
        "458,857"
      ],
      [
        "보험계약마진상각",
        "18,267,303",
        "-",
        "-",
        "18,267,303"
      ],
      [
        "손실회수배분",
        "(221,323)",
        "-",
        "-",
        "(221,323)"
      ],
      [
        "출재보험료경험조정",
        "(5,359,709)",
        "-",
        "-",
        "(5,359,709)"
      ],
      [
        "출재투자요소경험조정",
        "227,723",
        "-",
        "-",
        "227,723"
      ],
      [
        "보험료배분접근법적용비용",
        "12,646,540",
        "7,127,957",
        "968,340,455",
        "988,114,952"
      ],
      [
        "합 계",
        "41,429,071",
        "7,127,957",
        "968,340,455",
        "1,016,897,483"
      ]
    ],
    "footnotes": [],
    "_source_xml": "20250313001346_00761.xml"
  },
  {
    "caption": "당기 및 전기 중 보험계약 및 재보험계약에 대해 인식한 보험수익 및 재보험서비스비용의 내역은 다음과 같습니다.",
    "block_type": "mixed",
    "slice_label": "long_term",
    "slice_policy": "long_term",
    "mvp_candidate": true,
    "line_no": 19725,
    "score": 10,
    "reasons": [
      "caption: P&L keywords x2",
      "header: 1 measurement column",
      "rows: strong P&L stubs x3",
      "slice: long_term via non-PAA/GMM proxy"
    ],
    "header": [
      [
        "구 분",
        "장기",
        "자동차",
        "일반",
        "합계"
      ]
    ],
    "rows": [
      [
        "보험수익",
        "",
        "",
        "",
        ""
      ],
      [
        "예상보험금 및 보험서비스비용",
        "5,317,285,076",
        "-",
        "-",
        "5,317,285,076"
      ],
      [
        "위험조정변동",
        "130,628,669",
        "-",
        "-",
        "130,628,669"
      ],
      [
        "보험계약마진상각",
        "880,544,842",
        "-",
        "-",
        "880,544,842"
      ],
      [
        "손실요소배분",
        "(144,897,740)",
        "-",
        "-",
        "(144,897,740)"
      ],
      [
        "보험취득현금흐름상각",
        "741,747,826",
        "-",
        "-",
        "741,747,826"
      ],
      [
        "보험료배분접근법적용수익",
        "-",
        "4,239,174,196",
        "1,959,755,431",
        "6,198,929,626"
      ],
      [
        "합 계",
        "6,925,308,672",
        "4,239,174,196",
        "1,959,755,431",
        "13,124,238,299"
      ],
      [
        "재보험서비스비용",
        "",
        "",
        "",
        ""
      ],
      [
        "예상출재보험금 및 수입손해조사비",
        "14,683,693",
        "-",
        "-",
        "14,683,693"
      ],
      [
        "위험조정변동",
        "583,627",
        "-",
        "-",
        "583,627"
      ],
      [
        "보험계약마진상각",
        "7,689,161",
        "-",
        "-",
        "7,689,161"
      ],
      [
        "손실회수배분",
        "(60,262)",
        "-",
        "-",
        "(60,262)"
      ],
      [
        "출재보험료경험조정",
        "2,059,279",
        "-",
        "-",
        "2,059,279"
      ],
      [
        "출재투자요소경험조정",
        "(2,267,716)",
        "-",
        "-",
        "(2,267,716)"
      ],
      [
        "보험료배분접근법적용비용",
        "7,830,578",
        "5,528,107",
        "956,054,261",
        "969,412,946"
      ],
      [
        "합 계",
        "30,518,360",
        "5,528,107",
        "956,054,261",
        "992,100,728"
      ]
    ],
    "footnotes": [],
    "_source_xml": "20250313001346_00761.xml"
  },
  {
    "caption": "26. 보험계약 및 재보험계약(1) 보험계약부채 및 재보험계약자산의 변동당기 및 전기 중 현금흐름 및 당기손익과 기타포괄손익으로 인식한 장부금액의 변동은 다음과 같습니다. 1) 장기원수가. 당기",
    "block_type": "direct",
    "slice_label": "long_term",
    "slice_policy": "long_term",
    "mvp_candidate": true,
    "line_no": 21144,
    "score": 5,
    "reasons": [
      "header: 1 measurement column",
      "rows: strong P&L stubs x2",
      "slice: long_term label present"
    ],
    "header": [
      [
        "구분",
        "잔여보장부채",
        "발생사고부채",
        "합계"
      ],
      [
        "손실요소외",
        "손실요소",
        "최선추정",
        "위험조정"
      ]
    ],
    "rows": [
      [
        "기초보험계약부채",
        "22,079,298,247",
        "1,619,076,694",
        "2,213,355,436",
        "42,229,635",
        "25,953,960,012"
      ],
      [
        "기초보험계약자산",
        "-",
        "-",
        "-",
        "-",
        "-"
      ],
      [
        "기초순보험계약부채",
        "22,079,298,247",
        "1,619,076,694",
        "2,213,355,436",
        "42,229,635",
        "25,953,960,012"
      ],
      [
        "보험수익",
        "(7,481,394,159)",
        "-",
        "-",
        "-",
        "(7,481,394,159)"
      ],
      [
        "보험서비스비용",
        "897,379,455",
        "(276,719,282)",
        "5,911,716,948",
        "6,878,041",
        "6,539,255,162"
      ],
      [
        "실제보험금 및 보험서비스비용",
        "-",
        "(224,942,177)",
        "6,046,288,202",
        "66,716,254",
        "5,888,062,279"
      ],
      [
        "보험취득현금흐름상각",
        "875,811,972",
        "-",
        "-",
        "-",
        "875,811,972"
      ],
      [
        "발생사고부채 이행현금흐름 변동",
        "-",
        "-",
        "(134,571,254)",
        "(59,838,213)",
        "(194,409,467)"
      ],
      [
        "손실부담계약집합의 변동",
        "-",
        "(51,777,105)",
        "-",
        "-",
        "(51,777,105)"
      ],
      [
        "기타",
        "21,567,483",
        "-",
        "-",
        "-",
        "21,567,483"
      ],
      [
        "투자요소",
        "(2,978,721,221)",
        "-",
        "2,978,721,221",
        "-",
        "-"
      ],
      [
        "보험금융손익",
        "3,640,599,570",
        "76,890,989",
        "86,920,322",
        "-",
        "3,804,410,881"
      ],
      [
        "현금흐름",
        "9,098,956,470",
        "-",
        "(8,753,144,823)",
        "-",
        "345,811,647"
      ],
      [
        "수취한 보험료",
        "11,037,925,371",
        "-",
        "-",
        "-",
        "11,037,925,371"
      ],
      [
        "보험취득현금흐름",
        "(1,938,544,459)",
        "-",
        "-",
        "-",
        "(1,938,544,459)"
      ],
      [
        "보험금 및 보험서비스비용",
        "(424,442)",
        "-",
        "(8,803,350,165)",
        "-",
        "(8,803,774,607)"
      ],
      [
        "기타",
        "-",
        "-",
        "50,205,342",
        "-",
        "50,205,342"
      ],
      [
        "기말보험계약순부채",
        "25,256,118,362",
        "1,419,248,401",
        "2,437,569,104",
        "49,107,676",
        "29,162,043,543"
      ],
      [
        "기말보험계약부채",
        "25,256,118,362",
        "1,419,248,401",
        "2,437,569,104",
        "49,107,676",
        "29,162,043,543"
      ],
      [
        "기말보험계약자산",
        "-",
        "-",
        "-",
        "-",
        "-"
      ]
    ],
    "footnotes": [],
    "_source_xml": "20250313001346_00761.xml"
  }
]